{
    "module": "语言",
    "submodules": [
        {
            "title": "语言表达",
            "objectives": [
                {
                    "title": "发声能力",
                    "phasal_objectives": [
                        {
                            "index": "1.1",
                            "title": "发出不同的声音"
                        },
                        {
                            "index": "1.2",
                            "title": "发出有意义的声音"
                        }
                    ]
                },
                {
                    "title": "动作 / 手势沟通",
                    "phasal_objectives": [
                        {
                            "index": "2.1",
                            "title": "运用简单身体动作 / 手势来沟通"
                        },
                        {
                            "index": "2.2",
                            "title": "运用表达性身体动作 / 手势来沟通"
                        }
                    ]
                },
                {
                    "title": "模仿能力",
                    "phasal_objectives": [
                        {
                            "index": "3.1",
                            "title": "模仿动作"
                        },
                        {
                            "index": "3.2",
                            "title": "模仿玩玩具方法"
                        },
                        {
                            "index": "3.3",
                            "title": "模仿发声"
                        }
                    ]
                },
                {
                    "title": "词汇运用",
                    "phasal_objectives": [
                        {
                            "index": "4.1",
                            "title": "运用名词"
                        },
                        {
                            "index": "4.2",
                            "title": "运用动词"
                        },
                        {
                            "index": "4.3",
                            "title": "运用社交词汇"
                        },
                        {
                            "index": "4.4",
                            "title": "运用形容词"
                        },
                        {
                            "index": "4.5",
                            "title": "运用位置词"
                        },
                        {
                            "index": "4.6",
                            "title": "运用数词"
                        },
                        {
                            "index": "4.7",
                            "title": "运用量词"
                        },
                        {
                            "index": "4.8",
                            "title": "运用代名词"
                        },
                        {
                            "index": "4.9",
                            "title": "运用属有代名词"
                        },
                        {
                            "index": "4.10",
                            "title": "运用副词"
                        },
                        {
                            "index": "4.11",
                            "title": "运用时貌词"
                        },
                        {
                            "index": "4.12",
                            "title": "运用否定词"
                        },
                        {
                            "index": "4.13",
                            "title": "运用连接词"
                        }
                    ]
                },
                {
                    "title": "简单句子运用",
                    "phasal_objectives": [
                        {
                            "index": "5.1",
                            "title": "运用双词短句"
                        },
                        {
                            "index": "5.2",
                            "title": "运用三词句子"
                        },
                        {
                            "index": "5.3",
                            "title": "运用四词句子"
                        }
                    ]
                },
                {
                    "title": "复合句子运用",
                    "phasal_objectives": [
                        {
                            "index": "6.1",
                            "title": "运用不同的复合句子"
                        }
                    ]
                },
                {
                    "title": "问句运用",
                    "phasal_objectives": [
                        {
                            "index": "7.1",
                            "title": "运用不同的问句"
                        }
                    ]
                },
                {
                    "title": "语言思考",
                    "phasal_objectives": [
                        {
                            "index": "8.1",
                            "title": "词汇寻找 (归纳性)"
                        },
                        {
                            "index": "8.2",
                            "title": "词汇寻找 (扩散性)"
                        },
                        {
                            "index": "8.3",
                            "title": "词汇定义"
                        },
                        {
                            "index": "8.4",
                            "title": "比较异同"
                        },
                        {
                            "index": "8.5",
                            "title": "类比"
                        },
                        {
                            "index": "8.6",
                            "title": "程序概念"
                        },
                        {
                            "index": "8.7",
                            "title": "因果关系"
                        },
                        {
                            "index": "8.8",
                            "title": "解决问题"
                        },
                        {
                            "index": "8.9",
                            "title": "批判"
                        },
                        {
                            "index": "8.10",
                            "title": "推理能力"
                        }
                    ]
                },
                {
                    "title": "叙事能力",
                    "phasal_objectives": [
                        {
                            "index": "9.1",
                            "title": "叙述个人性事件"
                        },
                        {
                            "index": "9.2",
                            "title": "叙述一般性事件"
                        },
                        {
                            "index": "9.3",
                            "title": "叙述简单故事"
                        }
                    ]
                }
            ]
        },
        {
            "title": "语言理解",
            "objectives": [
                {
                    "title": "视觉反应",
                    "phasal_objectives": [
                        {
                            "index": "1.1",
                            "title": "目光专注"
                        },
                        {
                            "index": "1.2",
                            "title": "目光追视"
                        },
                        {
                            "index": "1.3",
                            "title": "目光转移"
                        }
                    ]
                },
                {
                    "title": "社交反应",
                    "phasal_objectives": [
                        {
                            "index": "2.1",
                            "title": "注视成人"
                        },
                        {
                            "index": "2.2",
                            "title": "追视成人"
                        }
                    ]
                },
                {
                    "title": "轮流作转技巧",
                    "phasal_objectives": [
                        {
                            "index": "3.1",
                            "title": "轮流玩玩具"
                        },
                        {
                            "index": "3.2",
                            "title": "轮流发声"
                        }
                    ]
                },
                {
                    "title": "配对技巧",
                    "phasal_objectives": [
                        {
                            "index": "4.1",
                            "title": "配对相同的符号"
                        },
                        {
                            "index": "4.2",
                            "title": "配对相似的符号"
                        }
                    ]
                },
                {
                    "title": "游戏技巧",
                    "phasal_objectives": [
                        {
                            "index": "5.1",
                            "title": "探索性游戏"
                        },
                        {
                            "index": "5.2",
                            "title": "功能性游戏"
                        },
                        {
                            "index": "5.3",
                            "title": "假想性游戏"
                        }
                    ]
                },
                {
                    "title": "听觉反应",
                    "phasal_objectives": [
                        {
                            "index": "6.1",
                            "title": "对声音作出反应"
                        },
                        {
                            "index": "6.2",
                            "title": "理解说话的语气"
                        }
                    ]
                },
                {
                    "title": "环境性理解",
                    "phasal_objectives": [
                        {
                            "index": "7.1",
                            "title": "对自己的名字作出反应"
                        },
                        {
                            "index": "7.2",
                            "title": "对生活的说话作出反应"
                        },
                        {
                            "index": "7.3",
                            "title": "理解“不”的意思"
                        },
                        {
                            "index": "7.4",
                            "title": "理解环境指令"
                        }
                    ]
                },
                {
                    "title": "日常指示理解",
                    "phasal_objectives": [
                        {
                            "index": "8.1",
                            "title": "理解日常指令"
                        },
                        {
                            "index": "8.2",
                            "title": "理解一个部分的指令"
                        }
                    ]
                },
                {
                    "title": "词汇理解",
                    "phasal_objectives": [
                        {
                            "index": "9.1",
                            "title": "理解名词"
                        },
                        {
                            "index": "9.2",
                            "title": "理解动词"
                        },
                        {
                            "index": "9.3",
                            "title": "理解形容词"
                        },
                        {
                            "index": "9.4",
                            "title": "理解位置词"
                        },
                        {
                            "index": "9.5",
                            "title": "理解数词"
                        },
                        {
                            "index": "9.6",
                            "title": "理解量词"
                        },
                        {
                            "index": "9.7",
                            "title": "理解代名词"
                        },
                        {
                            "index": "9.8",
                            "title": "理解属有代名词"
                        },
                        {
                            "index": "9.9",
                            "title": "理解副词"
                        },
                        {
                            "index": "9.10",
                            "title": "理解时貌词"
                        },
                        {
                            "index": "9.11",
                            "title": "理解否定词"
                        },
                        {
                            "index": "9.12",
                            "title": "理解连接词"
                        }
                    ]
                },
                {
                    "title": "简单句子理解",
                    "phasal_objectives": [
                        {
                            "index": "10.1",
                            "title": "理解双词短句"
                        },
                        {
                            "index": "10.2",
                            "title": "理解三词句子"
                        }
                    ]
                },
                {
                    "title": "复合句子理解",
                    "phasal_objectives": [
                        {
                            "index": "11.1",
                            "title": "理解不同的复合句子"
                        }
                    ]
                },
                {
                    "title": "问句理解",
                    "phasal_objectives": [
                        {
                            "index": "12.1",
                            "title": "理解不同的问句"
                        }
                    ]
                }
            ]
        }
    ]
}