{
  "domain": "语言表达篇",
  "age_range": "2-3岁",
  "macro_objective": "训练目标：发展对声音及字词的记忆力",
  "quests": [
    {
      "quest_name": "能重复含有 3—4 个音节的句子 (1) 重复简单的句子",
      "materials": [
        "玩偶",
        "图卡",
        "小零食",
        "小碗",
        "小杯子"
      ],
      "teaching_steps": "① 导师设计过家家的场景，可以用娃娃或玩偶，先示范说“请娃娃吃饼干”，同时把饼干递给娃娃。\n② 导师引导儿童说出“请娃娃吃饼干”。\n③ “请小熊喝水”“请娃娃吃饭”等操作方法同上。",
      "group_class_generalization": "① 学校生活中引导儿童在合适场景下说“帮我打开”“我要××”，才满足其需求。\n② 特殊儿童用问题行为表达需求时（如不要××就打人），特别注意适用此项训练法（教仿说“不要”，特别在问题行为出现前效果更佳，即使问题行为出现后也应重演正确表达过程）。",
      "home_generalization": "① 客人来访时，引导儿童说“请叔叔/阿姨喝水”；儿童有需要时，引导儿童说“请爸爸/妈妈帮忙”，问父母拿取物品；家庭聚餐，长辈入座时，引导儿童说“请爷爷/奶奶吃饭”等。\n② 特别注意左栏小组课第2条。"
    },
    {
      "quest_name": "能重复含有 3—4 个音节的句子 (2) 向别人传达简单的句子",
      "materials": [],
      "teaching_steps": "① 现场三人教学为佳（两个导师和一个儿童）。A导师站于略远处，B导师对儿童说“让A导师喝水”。然后拉起儿童手走近A导师，请儿童仿说“A导师，喝水”（若有难度，只要求对着A导师说“喝水”即可），A导师听罢喝水。\n② 此目标操作要点：传话。应先用大量示范让儿童理解传话的过程和语句取舍的要求。传话句子中涉及的语句均应符合儿童理解和表达能力。\n③ 待能掌握后，逐渐拉远被传话者的距离。\n④ 只有两人教学时可用娃娃代替第三人。",
      "group_class_generalization": "结合合适场景练习，大量练习。",
      "home_generalization": "饭前妈妈说“叫爸爸/爷爷/奶奶吃饭”，引导儿童逐一找到爸爸/爷爷/奶奶，并传话“爷爷吃饭”。一开始在生活中合适的固定场景下（如饭前）大量练习（每日三餐）向不同的人转述同一句话（吃饭），会有很好的练习效果。再随能力提升和泛化。"
    }
  ]
}